glyph_forge/__init__.py
glyph_forge/_version.py
glyph_forge/cli.py
glyph_forge/runner.py
glyph_forge/settings.py
glyph_forge/test.py
glyph_forge/core/__init__.py
glyph_forge/core/compression.py
glyph_forge/core/client/__init__.py
glyph_forge/core/client/exceptions.py
glyph_forge/core/client/forge_client.py
glyph_forge/core/workspace/__init__.py
glyph_forge/core/workspace/bootstrap.py
glyph_forge/core/workspace/config.py
glyph_forge/core/workspace/workspace.py
glyph_forge/core/workspace/examples/workspace_sample.py
glyph_forge/core/workspace/runtime/__init__.py
glyph_forge/core/workspace/runtime/engine.py
glyph_forge/core/workspace/runtime/adapters/__init__.py
glyph_forge/core/workspace/runtime/adapters/client.py
glyph_forge/core/workspace/runtime/adapters/local.py
glyph_forge/core/workspace/storage/__init__.py
glyph_forge/core/workspace/storage/base.py
glyph_forge/core/workspace/storage/fs.py
glyph_forge/core/workspace/storage/tagging.py
glyph/__init__.py
glyph/_version.py
glyph/cli.py
glyph/markup.py
glyph/runner.py
glyph/settings.py
glyph/core/analysis/__init__.py
glyph/core/analysis/aggregator.py
glyph/core/analysis/domain_scoring.py
glyph/core/analysis/features.py
glyph/core/analysis/matcher.py
glyph/core/analysis/context/context_enricher.py
glyph/core/analysis/context/context_tracker.py
glyph/core/analysis/context/heading_enricher.py
glyph/core/analysis/detectors/__init__.py
glyph/core/analysis/detectors/base.py
glyph/core/analysis/detectors/exact_matcher.py
glyph/core/analysis/detectors/heuristic_classifier.py
glyph/core/analysis/detectors/regex_maker.py
glyph/core/analysis/detectors/semantic_classifier.py
glyph/core/analysis/detectors/heuristics/callouts.py
glyph/core/analysis/detectors/heuristics/heading_detector.py
glyph/core/analysis/detectors/heuristics/list_detector.py
glyph/core/analysis/detectors/heuristics/paragraph_detector.py
glyph/core/analysis/detectors/heuristics/table_detector.py
glyph/core/analysis/detectors/utils/__init__.py
glyph_forge-2.1.0.dist-info/METADATA
glyph_forge-2.1.0.dist-info/WHEEL
glyph_forge-2.1.0.dist-info/entry_points.txt
glyph_forge-2.1.0.dist-info/licenses/LICENSE
glyph_forge-2.1.0.dist-info/RECORD
