Metadata-Version: 2.4
Name: glyph-forge
Version: 2.1.0
Summary: Pip installable client for Glyph Forge API
Project-URL: Homepage, https://www.glyphapi.ai/
Project-URL: Issues, https://github.com/Devpro-LLC/glyph-forge-client/issues
Project-URL: Source, https://github.com/Devpro-LLC/glyph-forge-client
Author: Devpro LLC
License: Apache-2.0
License-File: LICENSE
Classifier: License :: OSI Approved :: Apache Software License
Classifier: Operating System :: OS Independent
Classifier: Programming Language :: Python :: 3
Requires-Python: >=3.9
Requires-Dist: httpx>=0.25.0
Requires-Dist: lxml<6.0,>=5.2
Requires-Dist: python-docx<2.0,>=1.1
Provides-Extra: docs
Requires-Dist: furo>=2025.0.0; extra == 'docs'
Requires-Dist: myst-parser>=4.0.0; extra == 'docs'
Requires-Dist: sphinx-autodoc-typehints>=3.0.0; extra == 'docs'
Requires-Dist: sphinx-copybutton>=0.5.0; extra == 'docs'
Requires-Dist: sphinx>=8.0.0; extra == 'docs'
Provides-Extra: test
Requires-Dist: pytest-cov>=4.0.0; extra == 'test'
Requires-Dist: pytest>=7.0.0; extra == 'test'
